nextcord/ext/alternatives/__init__.py
nextcord/ext/alternatives/_common.py
nextcord/ext/alternatives/asset_converter.py
nextcord/ext/alternatives/binary_checks.py
nextcord/ext/alternatives/bot_send_help.py
nextcord/ext/alternatives/category_channel.py
nextcord/ext/alternatives/class_commands.py
nextcord/ext/alternatives/command_piping.py
nextcord/ext/alternatives/command_suffix.py
nextcord/ext/alternatives/converter_dict.py
nextcord/ext/alternatives/dict_converter.py
nextcord/ext/alternatives/fix_4098.py
nextcord/ext/alternatives/guild_converter.py
nextcord/ext/alternatives/inline_bot_commands.py
nextcord/ext/alternatives/int_map.py
nextcord/ext/alternatives/jump_url.py
nextcord/ext/alternatives/literal_converter.py
nextcord/ext/alternatives/material_colors.py
nextcord/ext/alternatives/material_colours.py
nextcord/ext/alternatives/menus_remove_reaction.py
nextcord/ext/alternatives/message_eq.py
nextcord/ext/alternatives/messageable_wait_for.py
nextcord/ext/alternatives/object_contains.py
nextcord/ext/alternatives/role.py
nextcord/ext/alternatives/silent_delete.py
nextcord/ext/alternatives/specific_error_handler.py
nextcord/ext/alternatives/subcommand_error.py
nextcord/ext/alternatives/webhook_channel.py
nextcord/ext/converters/__init__.py
nextcord/ext/converters/bot.py
nextcord/ext/converters/converter.py
nextcord/ext/converters/core.py
nextcord/ext/converters/model.py
nextcord/ext/events/__init__.py
nextcord/ext/events/_events.py
nextcord/ext/events/member_kick.py
nextcord/ext/events/mixins.py
nextcord/ext/events/utils.py
nextcord/ext/getch/__init__.py
nextcord/ext/getch/builder.py
nextcord/ext/getch/manager.py
nextcord/ext/getch/mixin.py
nextcord/ext/ipc/__init__.py
nextcord/ext/ipc/client.py
nextcord/ext/ipc/errors.py
nextcord/ext/ipc/server.py
nextcord/ext/menus/__init__.py
nextcord/ext/menus/constants.py
nextcord/ext/menus/exceptions.py
nextcord/ext/menus/menu_pages.py
nextcord/ext/menus/menus.py
nextcord/ext/menus/page_source.py
nextcord/ext/menus/utils.py
nextcord_ext_all-1.0.0.dist-info/METADATA
nextcord_ext_all-1.0.0.dist-info/WHEEL
nextcord_ext_all-1.0.0.dist-info/license
nextcord_ext_all-1.0.0.dist-info/top_level.txt
nextcord_ext_all-1.0.0.dist-info/RECORD
